{
	"song": {
		"splashSkin": "majinSplash",
		"arrowSkin": "majinNotes",
		"speed": 2.5,
		"stage": "voidscreen",
		"player1": "bfnew",
		"player2": "Mazin",
		"events": [],
		"notes": [
			{
				"gfSection": false,
				"altAnim": false,
				"sectionNotes": [],
				"bpm": 150,
				"sectionBeats": 4,
				"changeBPM": false,
				"mustHitSection": true
			},
			{
				"gfSection": false,
				"altAnim": false,
				"sectionNotes": [
					[
						1700,
						6,
						0
					],
					[
						1900,
						7,
						0
					],
					[
						2100,
						5,
						0
					],
					[
						2300,
						6,
						0
					],
					[
						2500,
						6,
						0
					],
					[
						2700,
						4,
						0
					],
					[
						2900,
						7,
						0
					],
					[
						3100,
						5,
						0
					]
				],
				"bpm": 150,
				"sectionBeats": 4,
				"changeBPM": false,
				"mustHitSection": true
			},
			{
				"gfSection": false,
				"altAnim": false,
				"sectionNotes": [
					[
						3300,
						4,
						0
					],
					[
						3400,
						4,
						0
					],
					[
						3500,
						6,
						100
					],
					[
						3700,
						7,
						100
					],
					[
						3900,
						5,
						0
					],
					[
						4100,
						4,
						95
					],
					[
						4400,
						5,
						100
					],
					[
						4600,
						6,
						0
					],
					[
						4272.15189873418,
						4,
						0
					]
				],
				"bpm": 150,
				"sectionBeats": 4,
				"changeBPM": false,
				"mustHitSection": true
			},
			{
				"gfSection": false,
				"altAnim": false,
				"sectionNotes": [
					[
						4800,
						7,
						500
					],
					[
						5400,
						7,
						0
					],
					[
						5600,
						5,
						500
					],
					[
						6200,
						6,
						0
					],
					[
						6300,
						5,
						100
					],
					[
						5506.32911392405,
						6,
						0
					]
				],
				"bpm": 150,
				"sectionBeats": 4,
				"changeBPM": false,
				"mustHitSection": true
			},
			{
				"gfSection": false,
				"altAnim": false,
				"sectionNotes": [
					[
						6500,
						4,
						0
					],
					[
						6700,
						5,
						100
					],
					[
						6900,
						6,
						0
					],
					[
						7100,
						7,
						300
					],
					[
						7500,
						4,
						200
					],
					[
						7800,
						6,
						900
					]
				],
				"bpm": 150,
				"sectionBeats": 4,
				"changeBPM": false,
				"mustHitSection": true
			},
			{
				"gfSection": false,
				"altAnim": false,
				"sectionNotes": [
					[
						7775.94936708861,
						2,
						0
					],
					[
						7975.94936708861,
						3,
						0
					],
					[
						8175.94936708861,
						1,
						0
					],
					[
						8375.94936708861,
						2,
						0
					],
					[
						8575.94936708861,
						2,
						0
					],
					[
						8775.94936708861,
						0,
						0
					],
					[
						8975.94936708861,
						3,
						0
					],
					[
						9175.94936708861,
						1,
						0
					]
				],
				"bpm": 150,
				"sectionBeats": 4,
				"changeBPM": false,
				"mustHitSection": true
			},
			{
				"gfSection": false,
				"altAnim": false,
				"sectionNotes": [
					[
						9375.94936708861,
						0,
						0
					],
					[
						9475.94936708861,
						0,
						0
					],
					[
						9575.94936708861,
						2,
						100
					],
					[
						9775.94936708861,
						3,
						100
					],
					[
						9975.94936708861,
						1,
						0
					],
					[
						10175.9493670886,
						0,
						95
					],
					[
						10475.9493670886,
						1,
						100
					],
					[
						10675.9493670886,
						2,
						0
					],
					[
						10348.1012658228,
						0,
						0
					]
				],
				"bpm": 150,
				"sectionBeats": 4,
				"changeBPM": false,
				"mustHitSection": true
			},
			{
				"gfSection": false,
				"altAnim": false,
				"sectionNotes": [
					[
						10875.9493670886,
						3,
						500
					],
					[
						11475.9493670886,
						3,
						0
					],
					[
						11675.9493670886,
						1,
						500
					],
					[
						12275.9493670886,
						2,
						0
					],
					[
						12375.9493670886,
						1,
						100
					],
					[
						11582.2784810127,
						2,
						0
					]
				],
				"bpm": 150,
				"sectionBeats": 4,
				"changeBPM": false,
				"mustHitSection": true
			},
			{
				"gfSection": false,
				"altAnim": false,
				"sectionNotes": [
					[
						12575.9493670886,
						0,
						0
					],
					[
						12775.9493670886,
						1,
						100
					],
					[
						12975.9493670886,
						2,
						0
					],
					[
						13175.9493670886,
						3,
						300
					],
					[
						13575.9493670886,
						0,
						200
					],
					[
						13875.9493670886,
						2,
						900
					]
				],
				"bpm": 150,
				"sectionBeats": 4,
				"changeBPM": false,
				"mustHitSection": true
			},
			{
				"gfSection": false,
				"altAnim": false,
				"sectionNotes": [
					[
						13955.6962025316,
						5,
						0
					],
					[
						14145.5696202532,
						5,
						0
					],
					[
						14240.5063291139,
						5,
						0
					],
					[
						14335.4430379747,
						5,
						0
					],
					[
						14525.3164556962,
						6,
						0
					],
					[
						14715.1898734177,
						4,
						95
					],
					[
						14905.0632911392,
						7,
						0
					],
					[
						15094.9367088608,
						6,
						285
					]
				],
				"bpm": 150,
				"sectionBeats": 4,
				"changeBPM": false,
				"mustHitSection": true
			},
			{
				"gfSection": false,
				"altAnim": false,
				"sectionNotes": [
					[
						15474.6835443038,
						7,
						0
					],
					[
						15664.5569620253,
						7,
						0
					],
					[
						15759.4936708861,
						7,
						0
					],
					[
						15854.4303797468,
						7,
						0
					],
					[
						16044.3037974684,
						5,
						95
					],
					[
						16234.1772151899,
						6,
						95
					],
					[
						16424.0506329114,
						7,
						0
					],
					[
						16518.9873417722,
						6,
						285
					]
				],
				"bpm": 150,
				"sectionBeats": 4,
				"changeBPM": false,
				"mustHitSection": true
			},
			{
				"gfSection": false,
				"altAnim": false,
				"sectionNotes": [
					[
						16993.6708860759,
						5,
						0
					],
					[
						17183.5443037975,
						5,
						0
					],
					[
						17278.4810126582,
						5,
						0
					],
					[
						17373.417721519,
						6,
						95
					],
					[
						17563.2911392405,
						4,
						0
					],
					[
						17753.164556962,
						7,
						0
					],
					[
						17848.1012658228,
						6,
						0
					],
					[
						17943.0379746835,
						5,
						0
					],
					[
						18037.9746835443,
						4,
						0
					],
					[
						18132.9113924051,
						5,
						95
					]
				],
				"bpm": 150,
				"sectionBeats": 4,
				"changeBPM": false,
				"mustHitSection": true
			},
			{
				"gfSection": false,
				"altAnim": false,
				"sectionNotes": [
					[
						18322.7848101266,
						4,
						0
					],
					[
						18512.6582278481,
						6,
						95
					],
					[
						18702.5316455696,
						5,
						0
					],
					[
						18797.4683544304,
						5,
						0
					],
					[
						18892.4050632911,
						6,
						95
					],
					[
						19082.2784810127,
						7,
						95
					],
					[
						19272.1518987342,
						5,
						95
					],
					[
						19462.0253164557,
						7,
						0
					],
					[
						19556.9620253165,
						6,
						0
					],
					[
						19651.8987341772,
						5,
						0
					]
				],
				"bpm": 150,
				"sectionBeats": 4,
				"changeBPM": false,
				"mustHitSection": true
			},
			{
				"gfSection": false,
				"altAnim": false,
				"sectionNotes": [
					[
						19841.7721518987,
						5,
						0
					],
					[
						20031.6455696203,
						6,
						669
					],
					[
						20791.1392405063,
						4,
						760
					]
				],
				"bpm": 150,
				"sectionBeats": 4,
				"changeBPM": false,
				"mustHitSection": true
			},
			{
				"gfSection": false,
				"altAnim": false,
				"sectionNotes": [
					[
						21645.5696202532,
						7,
						570
					],
					[
						22310.1265822785,
						5,
						570
					]
				],
				"bpm": 150,
				"sectionBeats": 4,
				"changeBPM": false,
				"mustHitSection": true
			},
			{
				"gfSection": false,
				"altAnim": false,
				"sectionNotes": [
					[
						22974.6835443038,
						6,
						1520
					]
				],
				"bpm": 150,
				"sectionBeats": 4,
				"changeBPM": false,
				"mustHitSection": true
			},
			{
				"gfSection": false,
				"altAnim": false,
				"sectionNotes": [
					[
						24588.6075949367,
						6,
						668
					]
				],
				"bpm": 150,
				"sectionBeats": 4,
				"changeBPM": false,
				"mustHitSection": true
			},
			{
				"gfSection": false,
				"altAnim": false,
				"sectionNotes": [],
				"bpm": 150,
				"sectionBeats": 4,
				"changeBPM": false,
				"mustHitSection": true
			},
			{
				"gfSection": false,
				"altAnim": false,
				"sectionNotes": [],
				"bpm": 150,
				"sectionBeats": 4,
				"changeBPM": false,
				"mustHitSection": true
			},
			{
				"gfSection": false,
				"altAnim": false,
				"sectionNotes": [],
				"bpm": 150,
				"sectionBeats": 4,
				"changeBPM": false,
				"mustHitSection": true
			},
			{
				"gfSection": false,
				"altAnim": false,
				"sectionNotes": [],
				"bpm": 150,
				"sectionBeats": 4,
				"changeBPM": false,
				"mustHitSection": true
			},
			{
				"gfSection": false,
				"altAnim": false,
				"sectionNotes": [],
				"bpm": 150,
				"sectionBeats": 4,
				"changeBPM": false,
				"mustHitSection": true
			},
			{
				"gfSection": false,
				"altAnim": false,
				"sectionNotes": [],
				"bpm": 150,
				"sectionBeats": 4,
				"changeBPM": false,
				"mustHitSection": true
			},
			{
				"gfSection": false,
				"altAnim": false,
				"sectionNotes": [],
				"bpm": 150,
				"sectionBeats": 4,
				"changeBPM": false,
				"mustHitSection": true
			},
			{
				"gfSection": false,
				"altAnim": false,
				"sectionNotes": [],
				"bpm": 150,
				"sectionBeats": 4,
				"changeBPM": false,
				"mustHitSection": true
			},
			{
				"gfSection": false,
				"altAnim": false,
				"sectionNotes": [],
				"bpm": 150,
				"sectionBeats": 4,
				"changeBPM": false,
				"mustHitSection": true
			},
			{
				"gfSection": false,
				"altAnim": false,
				"sectionNotes": [],
				"bpm": 150,
				"sectionBeats": 4,
				"changeBPM": false,
				"mustHitSection": true
			},
			{
				"gfSection": false,
				"altAnim": false,
				"sectionNotes": [],
				"bpm": 150,
				"sectionBeats": 4,
				"changeBPM": false,
				"mustHitSection": true
			},
			{
				"gfSection": false,
				"altAnim": false,
				"sectionNotes": [],
				"bpm": 150,
				"sectionBeats": 4,
				"changeBPM": false,
				"mustHitSection": true
			},
			{
				"gfSection": false,
				"altAnim": false,
				"sectionNotes": [],
				"bpm": 150,
				"sectionBeats": 4,
				"changeBPM": false,
				"mustHitSection": true
			},
			{
				"gfSection": false,
				"altAnim": false,
				"sectionNotes": [],
				"bpm": 150,
				"sectionBeats": 4,
				"changeBPM": false,
				"mustHitSection": true
			},
			{
				"gfSection": false,
				"altAnim": false,
				"sectionNotes": [],
				"bpm": 150,
				"sectionBeats": 4,
				"changeBPM": false,
				"mustHitSection": true
			},
			{
				"gfSection": false,
				"altAnim": false,
				"sectionNotes": [],
				"bpm": 150,
				"sectionBeats": 4,
				"changeBPM": false,
				"mustHitSection": true
			},
			{
				"gfSection": false,
				"altAnim": false,
				"sectionNotes": [],
				"bpm": 150,
				"sectionBeats": 4,
				"changeBPM": false,
				"mustHitSection": true
			},
			{
				"gfSection": false,
				"altAnim": false,
				"sectionNotes": [],
				"bpm": 150,
				"sectionBeats": 4,
				"changeBPM": false,
				"mustHitSection": true
			},
			{
				"gfSection": false,
				"altAnim": false,
				"sectionNotes": [],
				"bpm": 150,
				"sectionBeats": 4,
				"changeBPM": false,
				"mustHitSection": true
			},
			{
				"gfSection": false,
				"altAnim": false,
				"sectionNotes": [],
				"bpm": 150,
				"sectionBeats": 4,
				"changeBPM": false,
				"mustHitSection": true
			},
			{
				"gfSection": false,
				"altAnim": false,
				"sectionNotes": [],
				"bpm": 150,
				"sectionBeats": 4,
				"changeBPM": false,
				"mustHitSection": true
			},
			{
				"gfSection": false,
				"altAnim": false,
				"sectionNotes": [],
				"bpm": 150,
				"sectionBeats": 4,
				"changeBPM": false,
				"mustHitSection": true
			},
			{
				"gfSection": false,
				"altAnim": false,
				"sectionNotes": [],
				"bpm": 150,
				"sectionBeats": 4,
				"changeBPM": false,
				"mustHitSection": true
			},
			{
				"gfSection": false,
				"altAnim": false,
				"sectionNotes": [],
				"bpm": 150,
				"sectionBeats": 4,
				"changeBPM": false,
				"mustHitSection": true
			},
			{
				"gfSection": false,
				"altAnim": false,
				"sectionNotes": [],
				"bpm": 150,
				"sectionBeats": 4,
				"changeBPM": false,
				"mustHitSection": true
			},
			{
				"gfSection": false,
				"altAnim": false,
				"sectionNotes": [],
				"bpm": 150,
				"sectionBeats": 4,
				"changeBPM": false,
				"mustHitSection": true
			},
			{
				"gfSection": false,
				"altAnim": false,
				"sectionNotes": [],
				"bpm": 150,
				"sectionBeats": 4,
				"changeBPM": false,
				"mustHitSection": true
			},
			{
				"gfSection": false,
				"altAnim": false,
				"sectionNotes": [],
				"bpm": 150,
				"sectionBeats": 4,
				"changeBPM": false,
				"mustHitSection": true
			},
			{
				"gfSection": false,
				"altAnim": false,
				"sectionNotes": [],
				"bpm": 150,
				"sectionBeats": 4,
				"changeBPM": false,
				"mustHitSection": true
			},
			{
				"gfSection": false,
				"altAnim": false,
				"sectionNotes": [],
				"bpm": 150,
				"sectionBeats": 4,
				"changeBPM": false,
				"mustHitSection": true
			},
			{
				"gfSection": false,
				"altAnim": false,
				"sectionNotes": [],
				"bpm": 150,
				"sectionBeats": 4,
				"changeBPM": false,
				"mustHitSection": true
			},
			{
				"gfSection": false,
				"altAnim": false,
				"sectionNotes": [],
				"bpm": 150,
				"sectionBeats": 4,
				"changeBPM": false,
				"mustHitSection": true
			},
			{
				"gfSection": false,
				"altAnim": false,
				"sectionNotes": [],
				"bpm": 150,
				"sectionBeats": 4,
				"changeBPM": false,
				"mustHitSection": true
			},
			{
				"gfSection": false,
				"altAnim": false,
				"sectionNotes": [],
				"bpm": 150,
				"sectionBeats": 4,
				"changeBPM": false,
				"mustHitSection": true
			},
			{
				"gfSection": false,
				"altAnim": false,
				"sectionNotes": [],
				"bpm": 150,
				"sectionBeats": 4,
				"changeBPM": false,
				"mustHitSection": true
			},
			{
				"gfSection": false,
				"altAnim": false,
				"sectionNotes": [],
				"bpm": 150,
				"sectionBeats": 4,
				"changeBPM": false,
				"mustHitSection": true
			},
			{
				"gfSection": false,
				"altAnim": false,
				"sectionNotes": [],
				"bpm": 150,
				"sectionBeats": 4,
				"changeBPM": false,
				"mustHitSection": true
			},
			{
				"gfSection": false,
				"altAnim": false,
				"sectionNotes": [],
				"bpm": 150,
				"sectionBeats": 4,
				"changeBPM": false,
				"mustHitSection": true
			},
			{
				"gfSection": false,
				"altAnim": false,
				"sectionNotes": [],
				"bpm": 150,
				"sectionBeats": 4,
				"changeBPM": false,
				"mustHitSection": true
			},
			{
				"gfSection": false,
				"altAnim": false,
				"sectionNotes": [],
				"bpm": 150,
				"sectionBeats": 4,
				"changeBPM": false,
				"mustHitSection": true
			},
			{
				"gfSection": false,
				"altAnim": false,
				"sectionNotes": [],
				"bpm": 150,
				"sectionBeats": 4,
				"changeBPM": false,
				"mustHitSection": true
			},
			{
				"gfSection": false,
				"altAnim": false,
				"sectionNotes": [],
				"bpm": 150,
				"sectionBeats": 4,
				"changeBPM": false,
				"mustHitSection": true
			},
			{
				"gfSection": false,
				"altAnim": false,
				"sectionNotes": [],
				"bpm": 150,
				"sectionBeats": 4,
				"changeBPM": false,
				"mustHitSection": true
			},
			{
				"gfSection": false,
				"altAnim": false,
				"sectionNotes": [],
				"bpm": 150,
				"sectionBeats": 4,
				"changeBPM": false,
				"mustHitSection": true
			},
			{
				"gfSection": false,
				"altAnim": false,
				"sectionNotes": [],
				"bpm": 150,
				"sectionBeats": 4,
				"changeBPM": false,
				"mustHitSection": true
			},
			{
				"gfSection": false,
				"altAnim": false,
				"sectionNotes": [],
				"bpm": 150,
				"sectionBeats": 4,
				"changeBPM": false,
				"mustHitSection": true
			},
			{
				"gfSection": false,
				"altAnim": false,
				"sectionNotes": [],
				"bpm": 150,
				"sectionBeats": 4,
				"changeBPM": false,
				"mustHitSection": true
			},
			{
				"gfSection": false,
				"altAnim": false,
				"sectionNotes": [],
				"bpm": 150,
				"sectionBeats": 4,
				"changeBPM": false,
				"mustHitSection": true
			},
			{
				"gfSection": false,
				"altAnim": false,
				"sectionNotes": [],
				"bpm": 150,
				"sectionBeats": 4,
				"changeBPM": false,
				"mustHitSection": true
			},
			{
				"gfSection": false,
				"altAnim": false,
				"sectionNotes": [],
				"bpm": 158,
				"sectionBeats": 4,
				"changeBPM": false,
				"mustHitSection": true
			}
		],
		"gfVersion": "gf",
		"bpm": 158,
		"needsVoices": true,
		"song": "endeavours-v2"
	}
}